{
    "classes": [
        {
            "className": "file_open",
            "lineNumber": 9,
            "methods": [
                {
                    "access": "public",
                    "index": 0,
                    "name": "openFile",
                    "returnType": "QString"
                }
            ],
            "object": true,
            "qualifiedClassName": "file_open",
            "superClasses": [
                {
                    "access": "public",
                    "name": "QWidget"
                }
            ]
        }
    ],
    "inputFile": "file_open.h",
    "outputRevision": 69
}
